gladify/Gfile.py
gladify/Gmath.py
gladify/Gtext.py
gladify/__init__.py
gladify/GladUI/About.py
gladify/GladUI/App.py
gladify/GladUI/GladUI.png
gladify/GladUI/SoundPlayer.py
gladify/GladUI/Tools.py
gladify/GladUI/__init__.py
gladify-0.2.5.dist-info/LICENSE
gladify-0.2.5.dist-info/METADATA
gladify-0.2.5.dist-info/WHEEL
gladify-0.2.5.dist-info/top_level.txt
gladify-0.2.5.dist-info/RECORD
